README.rst
setup.py
sentry_logger/__init__.py
sentry_logger/sentry_logger.py
sentry_logger.egg-info/PKG-INFO
sentry_logger.egg-info/SOURCES.txt
sentry_logger.egg-info/dependency_links.txt
sentry_logger.egg-info/not-zip-safe
sentry_logger.egg-info/requires.txt
sentry_logger.egg-info/top_level.txt