Metadata-Version: 1.1
Name: sentry-logger
Version: 1.0
Summary: Basic helper for logging function / class based errors to sentry.io
Home-page: https://github.com/gurayinan/sentry_logger
Author: Guray Inan
Author-email: gurayinan@windowslive.com
License: MIT
Platform: UNKNOWN
Classifier: Development Status :: 3 - Alpha
Classifier: License :: OSI Approved :: MIT License
Classifier: Programming Language :: Python :: 3
Classifier: Topic :: Software Development :: Bug Tracking
